job_application_automator/__init__.py
job_application_automator/form_extractor.py
job_application_automator/form_filler.py
job_application_automator/mcp_server.py
job_application_automator/setup_claude.py
job_application_automator/mcp_config/__init__.py
job_application_automator-1.2.7.dist-info/licenses/LICENSE
job_application_automator-1.2.7.dist-info/METADATA
job_application_automator-1.2.7.dist-info/WHEEL
job_application_automator-1.2.7.dist-info/entry_points.txt
job_application_automator-1.2.7.dist-info/top_level.txt
job_application_automator-1.2.7.dist-info/RECORD
