Metadata-Version: 2.4
Name: job-application-automator
Version: 1.2.7
Summary: Automated job application form extraction, filling, and job matching with dual MCP server integration and smart prerequisites detection
Author-email: Job Automator Team <contact@jobautomator.dev>
License-Expression: MIT
Project-URL: Homepage, https://pypi.org/project/job-application-automator/
Project-URL: Documentation, https://pypi.org/project/job-application-automator/
Project-URL: Repository, https://github.com/your-username/job-application-automator
Project-URL: Issues, https://github.com/your-username/job-application-automator/issues
Keywords: mcp,job-application,automation,claude-desktop,form-filling,playwright,web-automation
Classifier: Development Status :: 4 - Beta
Classifier: Intended Audience :: Developers
Classifier: Operating System :: OS Independent
Classifier: Programming Language :: Python :: 3
Classifier: Programming Language :: Python :: 3.10
Classifier: Programming Language :: Python :: 3.11
Classifier: Programming Language :: Python :: 3.12
Classifier: Topic :: Software Development :: Libraries :: Python Modules
Classifier: Topic :: Office/Business
Classifier: Topic :: Internet :: WWW/HTTP :: Browsers
Requires-Python: >=3.10
License-File: LICENSE
Requires-Dist: mcp>=1.11.0
Requires-Dist: playwright>=1.40.0
Requires-Dist: undetected-playwright>=0.3.0
Requires-Dist: beautifulsoup4>=4.12.0
Requires-Dist: lxml>=4.9.0
Requires-Dist: requests>=2.28.0
Requires-Dist: geocoder>=1.38.1
Requires-Dist: pydantic>=2.0.0
Requires-Dist: typing-extensions>=4.8.0
Requires-Dist: httpx
Dynamic: license-file
